{
  "groups": [
    {
      "id": "score-time",
      "header": "Skóre/Čas",
      "cards": [
        {
          "title": "ACW Moving 25K",
          "mapUrl": "https://www.geoguessr.com/maps/62a44b22040f04bd36e8a914",
          "theme": "primary",
          "entries": [
            {
              "rank": "1.",
              "player": "Fabre",
              "playerUrl": "https://www.geoguessr.com/user/5e20d66d27ec1775f067c40c",
              "resultLabel": "00:03:07",
              "resultUrl": "https://www.geoguessr.com/results/txh5a1f6cAvyRiqp"
            },
            {
              "rank": "2.",
              "player": "Simi",
              "playerUrl": "https://www.geoguessr.com/user/59fc5f5c39d8552a6c5e81a2",
              "resultLabel": "00:08:18",
              "resultUrl": "https://www.geoguessr.com/results/faihB3a018V5jZj6"
            },
            {
              "rank": "3.",
              "player": "Daniel Samek",
              "playerUrl": "https://www.geoguessr.com/user/609c330b1415fe00017eb716",
              "resultLabel": "00:13:41",
              "resultUrl": "https://www.geoguessr.com/game/E58K0HHul0qfjpnd?shared"
            }
          ]
        },
        {
          "title": "ACW NM",
          "mapUrl": "https://www.geoguessr.com/maps/62a44b22040f04bd36e8a914",
          "theme": "secondary",
          "entries": [
            {
              "rank": "1.",
              "player": "Fabre",
              "playerUrl": "https://www.geoguessr.com/user/5e20d66d27ec1775f067c40c",
              "resultLabel": "25000",
              "resultUrl": "https://www.geoguessr.com/results/0ntMXFIEof9kxrpx"
            },
            {
              "rank": "2.",
              "player": "Daniel Samek",
              "playerUrl": "https://www.geoguessr.com/user/609c330b1415fe00017eb716",
              "resultLabel": "24512",
              "resultUrl": "https://www.geoguessr.com/game/wH353Sbyeo9Nep3q?shared"
            },
            {
              "rank": "3.",
              "player": "Babrnoch",
              "playerUrl": "https://www.geoguessr.com/user/676c36f3ae31f29e4b2ef2f5",
              "resultLabel": "24434",
              "resultUrl": "https://www.geoguessr.com/results/HbsApsxa47qqKILi"
            }
          ]
        },
        {
          "title": "ACW NMPZ",
          "mapUrl": "https://www.geoguessr.com/maps/62a44b22040f04bd36e8a914",
          "theme": "secondary",
          "entries": [
            {
              "rank": "1.",
              "player": "houmreu (Youtube)",
              "playerUrl": "https://www.geoguessr.com/user/5b571ce97135fa0e48b2d9f8",
              "resultLabel": "24895",
              "resultUrl": "https://www.geoguessr.com/game/yJ6lAIItIbvzQjNw"
            },
            {
              "rank": "2.",
              "player": "Daniel Samek",
              "playerUrl": "https://www.geoguessr.com/user/609c330b1415fe00017eb716",
              "resultLabel": "24549",
              "resultUrl": "https://www.geoguessr.com/game/pdS5TBR60OQuA22v?shared"
            },
            {
              "rank": "3.",
              "player": "Fabre",
              "playerUrl": "https://www.geoguessr.com/user/5e20d66d27ec1775f067c40c",
              "resultLabel": "24535",
              "resultUrl": "https://www.geoguessr.com/results/8wWV7ycwUK6NZxDu"
            }
          ]
        },
        {
          "title": "AI Generated World 25K",
          "mapUrl": "https://www.geoguessr.com/maps/5dbaf08ed0d2a478444d2e8e",
          "theme": "primary",
          "entries": [
            {
              "rank": "1.",
              "player": "Fabre",
              "playerUrl": "https://www.geoguessr.com/user/5e20d66d27ec1775f067c40c",
              "resultLabel": "00:08:48",
              "resultUrl": "https://www.geoguessr.com/results/k02a1tYTuMlIrzma"
            },
            {
              "rank": "2.",
              "player": "-",
              "playerUrl": null,
              "resultLabel": "-",
              "resultUrl": null
            },
            {
              "rank": "3.",
              "player": "-",
              "playerUrl": null,
              "resultLabel": "-",
              "resultUrl": null
            }
          ]
        },
        {
          "title": "AI Generated World NM",
          "mapUrl": "https://www.geoguessr.com/maps/5dbaf08ed0d2a478444d2e8e",
          "theme": "secondary",
          "entries": [
            {
              "rank": "1.",
              "player": "Daniel Samek",
              "playerUrl": "https://www.geoguessr.com/user/609c330b1415fe00017eb716",
              "resultLabel": "24612",
              "resultUrl": "https://www.geoguessr.com/game/7mrsHTFV6hvAC2Zr?shared"
            },
            {
              "rank": "2.",
              "player": "houmreu (Youtube)",
              "playerUrl": "https://www.geoguessr.com/user/5b571ce97135fa0e48b2d9f8",
              "resultLabel": "24495",
              "resultUrl": "https://www.geoguessr.com/results/AKo8mwZoiOpQ8Bfp"
            },
            {
              "rank": "3.",
              "player": "Zakerr",
              "playerUrl": "https://www.geoguessr.com/user/5ec3b73d97c8ee199c573937",
              "resultLabel": "24425",
              "resultUrl": "https://www.geoguessr.com/results/XSe9cyPmntLR1JtH"
            }
          ]
        },
        {
          "title": "AI Generated World NMPZ",
          "mapUrl": "https://www.geoguessr.com/maps/5dbaf08ed0d2a478444d2e8e",
          "theme": "secondary",
          "entries": [
            {
              "rank": "1.",
              "player": "Fabre",
              "playerUrl": "https://www.geoguessr.com/user/5e20d66d27ec1775f067c40c",
              "resultLabel": "24889",
              "resultUrl": "https://www.geoguessr.com/results/34hksfRJEDnk0nPt"
            },
            {
              "rank": "2.",
              "player": "Babrnoch",
              "playerUrl": "https://www.geoguessr.com/user/676c36f3ae31f29e4b2ef2f5",
              "resultLabel": "22738",
              "resultUrl": "https://www.geoguessr.com/game/r6fCqVzBOPrQEJ3X"
            },
            {
              "rank": "3.",
              "player": "Daniel Samek",
              "playerUrl": "https://www.geoguessr.com/user/609c330b1415fe00017eb716",
              "resultLabel": "22413",
              "resultUrl": "https://www.geoguessr.com/game/M7HXUt3EccbutSDw?shared"
            }
          ]
        },
        {
          "title": "An Arbitrary World 25K",
          "mapUrl": "https://www.geoguessr.com/maps/6089bfcff6a0770001f645dd",
          "theme": "primary",
          "entries": [
            {
              "rank": "1.",
              "player": "Intruder",
              "playerUrl": "https://www.geoguessr.com/user/5e20d66d27ec1775f067c40c",
              "resultLabel": "00:16:58",
              "resultUrl": "https://www.geoguessr.com/game/AxpavqNtxy7nm8Cg"
            },
            {
              "rank": "2.",
              "player": "-",
              "playerUrl": null,
              "resultLabel": "-",
              "resultUrl": null
            },
            {
              "rank": "3.",
              "player": "-",
              "playerUrl": null,
              "resultLabel": "-",
              "resultUrl": null
            }
          ]
        },
        {
          "title": "An Arbitrary World NM",
          "mapUrl": "https://www.geoguessr.com/maps/6089bfcff6a0770001f645dd",
          "theme": "secondary",
          "entries": [
            {
              "rank": "1.",
              "player": "Babrnoch",
              "playerUrl": "https://www.geoguessr.com/user/676c36f3ae31f29e4b2ef2f5",
              "resultLabel": "24661",
              "resultUrl": "https://www.geoguessr.com/results/7VJn3uN63XWR05gC"
            },
            {
              "rank": "2.",
              "player": "kaerdna",
              "playerUrl": "https://www.geoguessr.com/user/5ef9c663e454364894a3fecc",
              "resultLabel": "24622",
              "resultUrl": "https://www.geoguessr.com/results/d2FIu0CBab5pfDbX"
            },
            {
              "rank": "3.",
              "player": "Daniel Samek",
              "playerUrl": "https://www.geoguessr.com/user/609c330b1415fe00017eb716",
              "resultLabel": "24559",
              "resultUrl": "https://www.geoguessr.com/game/leztyHhd7fXFeERn?shared"
            }
          ]
        },
        {
          "title": "An Arbitrary World NMPZ",
          "mapUrl": "https://www.geoguessr.com/maps/6089bfcff6a0770001f645dd",
          "theme": "secondary",
          "entries": [
            {
              "rank": "1.",
              "player": "Fabre",
              "playerUrl": "https://www.geoguessr.com/user/5e20d66d27ec1775f067c40c",
              "resultLabel": "24889",
              "resultUrl": "https://www.geoguessr.com/results/uKp7ayhdoONgzMQb"
            },
            {
              "rank": "2.",
              "player": "Intruder",
              "playerUrl": "https://www.geoguessr.com/user/5e20d66d27ec1775f067c40c",
              "resultLabel": "24759",
              "resultUrl": "https://www.geoguessr.com/results/6djaFmB77HDtgtZc"
            },
            {
              "rank": "3.",
              "player": "houmreu (Youtube)",
              "playerUrl": "https://www.geoguessr.com/user/5b571ce97135fa0e48b2d9f8",
              "resultLabel": "24688",
              "resultUrl": "https://www.geoguessr.com/results/d0AyLAHSpbpmYcpm"
            }
          ]
        },
        {
          "title": "Česko/Slovensko 25K",
          "mapUrl": "https://www.geoguessr.com/maps/64c38117ef02543defebb815",
          "theme": "primary",
          "entries": [
            {
              "rank": "1.",
              "player": "Darwicek",
              "playerUrl": "https://www.geoguessr.com/user/5eb28849eb473f5b68091713",
              "resultLabel": "00:08:57",
              "resultUrl": "https://www.geoguessr.com/results/dE5qhAUbcrGYKuvp"
            },
            {
              "rank": "2.",
              "player": "kaerdna",
              "playerUrl": "https://www.geoguessr.com/user/5ef9c663e454364894a3fecc",
              "resultLabel": "00:09:16",
              "resultUrl": "https://www.geoguessr.com/results/2KyCaRy4Sttzum4b"
            },
            {
              "rank": "3.",
              "player": "Gold50",
              "playerUrl": "https://www.geoguessr.com/user/62f16e172d6c9c8c59887583",
              "resultLabel": "00:09:26",
              "resultUrl": "https://www.geoguessr.com/results/W5LqEbTaI1AcDoem"
            }
          ]
        },
        {
          "title": "Česko/Slovensko NM",
          "mapUrl": "https://www.geoguessr.com/maps/64c38117ef02543defebb815",
          "theme": "secondary",
          "entries": [
            {
              "rank": "1.",
              "player": "houmreu (Youtube)",
              "playerUrl": "https://www.geoguessr.com/user/5b571ce97135fa0e48b2d9f8",
              "resultLabel": "21007",
              "resultUrl": "https://www.geoguessr.com/results/tSjN1MyTOlyzdVNK"
            },
            {
              "rank": "2.",
              "player": "kaerdna",
              "playerUrl": "https://www.geoguessr.com/user/5ef9c663e454364894a3fecc",
              "resultLabel": "19359",
              "resultUrl": "https://www.geoguessr.com/results/qjqsLsMYYYSpbZ66"
            },
            {
              "rank": "3.",
              "player": "Darwicek",
              "playerUrl": "https://www.geoguessr.com/user/5eb28849eb473f5b68091713",
              "resultLabel": "18769",
              "resultUrl": "https://www.geoguessr.com/results/OUoXCXNCNPDiJA2R"
            }
          ]
        },
        {
          "title": "Česko/Slovensko NMPZ",
          "mapUrl": "https://www.geoguessr.com/maps/64c38117ef02543defebb815",
          "theme": "secondary",
          "entries": [
            {
              "rank": "1.",
              "player": "kaerdna",
              "playerUrl": "https://www.geoguessr.com/user/5ef9c663e454364894a3fecc",
              "resultLabel": "20012",
              "resultUrl": "https://www.geoguessr.com/results/Kc62BIjfWoN3odOg"
            },
            {
              "rank": "2.",
              "player": "houmreu (Youtube)",
              "playerUrl": "https://www.geoguessr.com/user/5b571ce97135fa0e48b2d9f8",
              "resultLabel": "16606",
              "resultUrl": "https://www.geoguessr.com/results/YsmPvLx1TWgg5dRC"
            },
            {
              "rank": "3.",
              "player": "Raspberry",
              "playerUrl": "https://www.geoguessr.com/user/5e88bac13d4b6a2d8ca9f5a9",
              "resultLabel": "16382",
              "resultUrl": "https://www.geoguessr.com/game/k0BHn2baERah5sYb"
            }
          ]
        },
        {
          "title": "Česko 25K",
          "mapUrl": "https://www.geoguessr.com/maps/czech-republic",
          "theme": "primary",
          "entries": [
            {
              "rank": "1.",
              "player": "Fabre",
              "playerUrl": "https://www.geoguessr.com/user/5e20d66d27ec1775f067c40c",
              "resultLabel": "00:02:15",
              "resultUrl": "https://www.geoguessr.com/results/d7XL7xRLz2qXczDT"
            },
            {
              "rank": "2.",
              "player": "kaerdna",
              "playerUrl": "https://www.geoguessr.com/user/5ef9c663e454364894a3fecc",
              "resultLabel": "00:02:44",
              "resultUrl": "https://www.geoguessr.com/results/i6TLup8PyvraTwn9"
            },
            {
              "rank": "3.",
              "player": "Darwicek",
              "playerUrl": "https://www.geoguessr.com/user/5eb28849eb473f5b68091713",
              "resultLabel": "00:04:12",
              "resultUrl": "https://www.geoguessr.com/results/SLX2MrJK6SkqtqvM"
            }
          ]
        },
        {
          "title": "Česko NM",
          "mapUrl": "https://www.geoguessr.com/maps/czech-republic",
          "theme": "secondary",
          "entries": [
            {
              "rank": "1.",
              "player": "kaerdna",
              "playerUrl": "https://www.geoguessr.com/user/5ef9c663e454364894a3fecc",
              "resultLabel": "25000",
              "resultUrl": "https://www.geoguessr.com/results/OPdCXUDcNu0R7oQR"
            },
            {
              "rank": "2.",
              "player": "Darwicek",
              "playerUrl": "https://www.geoguessr.com/user/5eb28849eb473f5b68091713",
              "resultLabel": "24623",
              "resultUrl": "https://www.geoguessr.com/results/Yy7wBWjLAsMgVYTV"
            },
            {
              "rank": "3.",
              "player": "Bcz_Mvn",
              "playerUrl": "https://www.geoguessr.com/user/62db0638584b2b27a12958df",
              "resultLabel": "23928",
              "resultUrl": "https://www.geoguessr.com/game/PBUlnK0nqioRr9rN"
            }
          ]
        },
        {
          "title": "Česko NMPZ",
          "mapUrl": "https://www.geoguessr.com/maps/czech-republic",
          "theme": "secondary",
          "entries": [
            {
              "rank": "1.",
              "player": "kaerdna",
              "playerUrl": "https://www.geoguessr.com/user/5ef9c663e454364894a3fecc",
              "resultLabel": "22100",
              "resultUrl": "https://www.geoguessr.com/results/fXTt1HjWnfNVCK2z"
            },
            {
              "rank": "2.",
              "player": "Bcz_Mvn",
              "playerUrl": "https://www.geoguessr.com/user/62db0638584b2b27a12958df",
              "resultLabel": "18293",
              "resultUrl": "https://www.geoguessr.com/game/Y0BHAWOvBe47wcJR"
            },
            {
              "rank": "3.",
              "player": "Nofl (Raspberry)",
              "playerUrl": "https://www.geoguessr.com/user/5e88bac13d4b6a2d8ca9f5a9",
              "resultLabel": "17298",
              "resultUrl": "https://www.geoguessr.com/game/QvVUf9HDyZSEYbQR"
            }
          ]
        },
        {
          "title": "Slovensko 25K",
          "mapUrl": "https://www.geoguessr.com/maps/slovakia",
          "theme": "primary",
          "entries": [
            {
              "rank": "1.",
              "player": "milosgo",
              "playerUrl": "https://www.geoguessr.com/user/589506d22f6fc615a834e45a",
              "resultLabel": "00:02:45",
              "resultUrl": "https://www.geoguessr.com/game/wepJ0Koy5KsRwrRl?shared"
            },
            {
              "rank": "2.",
              "player": "Sebastian",
              "playerUrl": "https://www.geoguessr.com/user/6093de001b4a920001509f1f",
              "resultLabel": "00:03:17",
              "resultUrl": "https://www.geoguessr.com/results/aJJ0uy4s55JUXble"
            },
            {
              "rank": "3.",
              "player": "Zakerr",
              "playerUrl": "https://www.geoguessr.com/user/5ec3b73d97c8ee199c573937",
              "resultLabel": "00:05:14",
              "resultUrl": "https://www.geoguessr.com/results/j9lVHS9IHRdaYkjg"
            }
          ]
        },
        {
          "title": "Slovensko NM",
          "mapUrl": "https://www.geoguessr.com/maps/slovakia",
          "theme": "secondary",
          "entries": [
            {
              "rank": "1.",
              "player": "milosgo",
              "playerUrl": "https://www.geoguessr.com/user/589506d22f6fc615a834e45a",
              "resultLabel": "24258",
              "resultUrl": "https://www.geoguessr.com/game/d1XljQkNNDw5IyzF?shared"
            },
            {
              "rank": "2.",
              "player": "Noice.",
              "playerUrl": "https://www.geoguessr.com/user/5ddc41cc6a1dd6323081da84",
              "resultLabel": "23171",
              "resultUrl": "https://www.geoguessr.com/results/NCVOAGgwYZ9pOHiI"
            },
            {
              "rank": "3.",
              "player": "Zakerr",
              "playerUrl": "https://www.geoguessr.com/user/5ec3b73d97c8ee199c573937",
              "resultLabel": "21743",
              "resultUrl": "https://www.geoguessr.com/results/tSoXmYN3G1ajOdj1"
            }
          ]
        },
        {
          "title": "Slovensko NMPZ",
          "mapUrl": "https://www.geoguessr.com/maps/slovakia",
          "theme": "secondary",
          "entries": [
            {
              "rank": "1.",
              "player": "milosgo",
              "playerUrl": "https://www.geoguessr.com/user/589506d22f6fc615a834e45a",
              "resultLabel": "22498",
              "resultUrl": "https://www.geoguessr.com/game/ftW5igQeNYsy93vp?shared"
            },
            {
              "rank": "3.",
              "player": "Bcz_Mvn",
              "playerUrl": "https://www.geoguessr.com/user/62db0638584b2b27a12958df",
              "resultLabel": "17187",
              "resultUrl": "https://www.geoguessr.com/game/6FJknZbB3Nw78xnH"
            },
            {
              "rank": "3.",
              "player": "Nofl (Raspberry)",
              "playerUrl": "https://www.geoguessr.com/user/5e88bac13d4b6a2d8ca9f5a9",
              "resultLabel": "16290",
              "resultUrl": "https://www.geoguessr.com/game/yc7txLjHb9KniV5L"
            }
          ]
        },
        {
          "title": "An Arbitrary Europe 25K",
          "mapUrl": "https://www.geoguessr.com/maps/60788ebfb15d750001929514",
          "theme": "primary",
          "entries": [
            {
              "rank": "1.",
              "player": "Intruder",
              "playerUrl": "https://www.geoguessr.com/user/5e20d66d27ec1775f067c40c",
              "resultLabel": "00:12:02",
              "resultUrl": "https://www.geoguessr.com/game/4cUdjBey6s0DwzhA"
            },
            {
              "rank": "2.",
              "player": "kaerdna",
              "playerUrl": "https://www.geoguessr.com/user/5ef9c663e454364894a3fecc",
              "resultLabel": "00:19:41",
              "resultUrl": "https://www.geoguessr.com/results/9aKOxXaGHwGyMhrD"
            },
            {
              "rank": "3.",
              "player": "Juxerr",
              "playerUrl": "https://www.geoguessr.com/user/63232556fe765bafba5ef084",
              "resultLabel": "00:45:29",
              "resultUrl": "https://www.geoguessr.com/results/c5DPfJYrMTyHScNf"
            }
          ]
        },
        {
          "title": "An Arbitrary Europe NM",
          "mapUrl": "https://www.geoguessr.com/maps/60788ebfb15d750001929514",
          "theme": "secondary",
          "entries": [
            {
              "rank": "1.",
              "player": "Nofl (Raspberry)",
              "playerUrl": "https://www.geoguessr.com/user/5e88bac13d4b6a2d8ca9f5a9",
              "resultLabel": "23920",
              "resultUrl": "https://www.geoguessr.com/results/xLRYY0jhXDqwFO6h"
            },
            {
              "rank": "2.",
              "player": "kaerdna",
              "playerUrl": "https://www.geoguessr.com/user/5ef9c663e454364894a3fecc",
              "resultLabel": "23681",
              "resultUrl": "https://www.geoguessr.com/results/hh9vLQgMB88OfXzz"
            },
            {
              "rank": "3.",
              "player": "Juxerr",
              "playerUrl": "https://www.geoguessr.com/user/63232556fe765bafba5ef084",
              "resultLabel": "23241",
              "resultUrl": "https://www.geoguessr.com/results/BP0318Dr8s2RHJX6"
            }
          ]
        },
        {
          "title": "An Arbitrary Europe NMPZ",
          "mapUrl": "https://www.geoguessr.com/maps/60788ebfb15d750001929514",
          "theme": "secondary",
          "entries": [
            {
              "rank": "1.",
              "player": "Filipes",
              "playerUrl": "https://www.geoguessr.com/user/60d61ea5548abb000175dd7c",
              "resultLabel": "24236",
              "resultUrl": "https://www.youtube.com/watch?v=_i1qHO0a67k"
            },
            {
              "rank": "2.",
              "player": "Raspberry",
              "playerUrl": "https://www.geoguessr.com/user/5e88bac13d4b6a2d8ca9f5a9",
              "resultLabel": "22797",
              "resultUrl": "https://www.geoguessr.com/game/D9ryLMSQYknvwPIs"
            },
            {
              "rank": "3.",
              "player": "houmreu (Youtube)",
              "playerUrl": "https://www.geoguessr.com/user/5b571ce97135fa0e48b2d9f8",
              "resultLabel": "22384",
              "resultUrl": "https://www.geoguessr.com/game/87WMEVd5ILN2bgwO"
            }
          ]
        },
        {
          "title": "Extreme Regionguessing 25K",
          "mapUrl": "https://www.geoguessr.com/maps/63cfd5ba9512ebc734807d3d",
          "theme": "primary",
          "entries": [
            {
              "rank": "1.",
              "player": "Fabre",
              "playerUrl": "https://www.geoguessr.com/user/5e20d66d27ec1775f067c40c",
              "resultLabel": "00:08:11",
              "resultUrl": "https://www.geoguessr.com/results/XFUKNUiPcBBmyj7b"
            },
            {
              "rank": "2.",
              "player": "-",
              "playerUrl": null,
              "resultLabel": "-",
              "resultUrl": null
            },
            {
              "rank": "3.",
              "player": "-",
              "playerUrl": null,
              "resultLabel": "-",
              "resultUrl": null
            }
          ]
        },
        {
          "title": "Extreme Regionguessing NM",
          "mapUrl": "https://www.geoguessr.com/maps/63cfd5ba9512ebc734807d3d",
          "theme": "secondary",
          "entries": [
            {
              "rank": "1.",
              "player": "Zakerr",
              "playerUrl": "https://www.geoguessr.com/user/5ec3b73d97c8ee199c573937",
              "resultLabel": "23931",
              "resultUrl": "https://www.geoguessr.com/results/ZWn1S9mrKiosCZPo"
            },
            {
              "rank": "2.",
              "player": "houmreu (Youtube)",
              "playerUrl": "https://www.geoguessr.com/user/5b571ce97135fa0e48b2d9f8",
              "resultLabel": "22797",
              "resultUrl": "https://www.geoguessr.com/results/OKKIxoAniexYvrXH"
            },
            {
              "rank": "3.",
              "player": "kaerdna",
              "playerUrl": "https://www.geoguessr.com/user/5ef9c663e454364894a3fecc",
              "resultLabel": "22482",
              "resultUrl": "https://www.geoguessr.com/results/KWsXbtq5FwErjVhl"
            }
          ]
        },
        {
          "title": "Extreme Regionguessing NMPZ",
          "mapUrl": "https://www.geoguessr.com/maps/63cfd5ba9512ebc734807d3d",
          "theme": "secondary",
          "entries": [
            {
              "rank": "1.",
              "player": "Juxerr",
              "playerUrl": "https://www.geoguessr.com/user/63232556fe765bafba5ef084",
              "resultLabel": "23193",
              "resultUrl": "https://www.geoguessr.com/results/F91V82nnXD8sDw5O"
            },
            {
              "rank": "2.",
              "player": "frams",
              "playerUrl": "https://www.geoguessr.com/user/639d31b056418a9903a7a3ba",
              "resultLabel": "21853",
              "resultUrl": "https://www.geoguessr.com/game/1io5jtGZMKlfJVyY"
            },
            {
              "rank": "3.",
              "player": "Babrnoch",
              "playerUrl": "https://www.geoguessr.com/user/676c36f3ae31f29e4b2ef2f5",
              "resultLabel": "21188",
              "resultUrl": "https://www.geoguessr.com/game/jgNyxq6tsKwvOyV7"
            }
          ]
        },
        {
          "title": "An Arbitrary Rural World 25K",
          "mapUrl": "https://www.geoguessr.com/maps/643dbc7ccc47d3a344307998",
          "theme": "primary",
          "entries": [
            {
              "rank": "1.",
              "player": "Intruder",
              "playerUrl": "https://www.geoguessr.com/user/5e20d66d27ec1775f067c40c",
              "resultLabel": "00:14:55",
              "resultUrl": "https://www.geoguessr.com/game/4pm0DIjGMEajYf1E"
            },
            {
              "rank": "2.",
              "player": "-",
              "playerUrl": null,
              "resultLabel": "-",
              "resultUrl": null
            },
            {
              "rank": "3.",
              "player": "-",
              "playerUrl": null,
              "resultLabel": "-",
              "resultUrl": null
            }
          ]
        },
        {
          "title": "An Arbitrary Rural World NM",
          "mapUrl": "https://www.geoguessr.com/maps/643dbc7ccc47d3a344307998",
          "theme": "secondary",
          "entries": [
            {
              "rank": "1.",
              "player": "houmreu (Youtube)",
              "playerUrl": "https://www.geoguessr.com/user/5b571ce97135fa0e48b2d9f8",
              "resultLabel": "24268",
              "resultUrl": "https://www.geoguessr.com/results/9QWpeCAZmYzOO133"
            },
            {
              "rank": "2.",
              "player": "Mikebarry",
              "playerUrl": "https://www.geoguessr.com/user/651abda886200fcd9cf22b7a",
              "resultLabel": "24122",
              "resultUrl": "https://www.geoguessr.com/results/Bw1L4LW76E4NWiFu"
            },
            {
              "rank": "3.",
              "player": "Babrnoch",
              "playerUrl": "https://www.geoguessr.com/user/676c36f3ae31f29e4b2ef2f5",
              "resultLabel": "24047",
              "resultUrl": "https://www.geoguessr.com/results/R15GM5FdUzpZYSFa"
            }
          ]
        },
        {
          "title": "An Arbitrary Rural World NMPZ",
          "mapUrl": "https://www.geoguessr.com/maps/643dbc7ccc47d3a344307998",
          "theme": "secondary",
          "entries": [
            {
              "rank": "1.",
              "player": "Zakerr",
              "playerUrl": "https://www.geoguessr.com/user/5ec3b73d97c8ee199c573937",
              "resultLabel": "24800",
              "resultUrl": "https://www.geoguessr.com/results/7bheLeqLSoGh07ch"
            },
            {
              "rank": "2.",
              "player": "houmreu (Youtube)",
              "playerUrl": "https://www.geoguessr.com/user/5b571ce97135fa0e48b2d9f8",
              "resultLabel": "24521",
              "resultUrl": "https://www.geoguessr.com/results/v35M824XfeOyZIlz"
            },
            {
              "rank": "3.",
              "player": "-",
              "playerUrl": null,
              "resultLabel": "-",
              "resultUrl": null
            }
          ]
        },
        {
          "title": "Dirty World 25K",
          "mapUrl": "https://www.geoguessr.com/maps/63f3ff1e0355e40ded075e0c",
          "theme": "secondary",
          "entries": [
            {
              "rank": "1.",
              "player": "Intruder",
              "playerUrl": "https://www.geoguessr.com/user/5e20d66d27ec1775f067c40c",
              "resultLabel": "00:17:12",
              "resultUrl": "https://www.geoguessr.com/game/FXRbdxvtUDzyuLwa"
            },
            {
              "rank": "2.",
              "player": "-",
              "playerUrl": null,
              "resultLabel": "-",
              "resultUrl": null
            },
            {
              "rank": "3.",
              "player": "-",
              "playerUrl": null,
              "resultLabel": "-",
              "resultUrl": null
            }
          ]
        },
        {
          "title": "Dirty World NM",
          "mapUrl": "https://www.geoguessr.com/maps/63f3ff1e0355e40ded075e0c",
          "theme": "secondary",
          "entries": [
            {
              "rank": "1.",
              "player": "Zakerr",
              "playerUrl": "https://www.geoguessr.com/user/5ec3b73d97c8ee199c573937",
              "resultLabel": "24375",
              "resultUrl": "https://www.geoguessr.com/results/hOiDUqE2nfbSX7IA"
            },
            {
              "rank": "2.",
              "player": "-",
              "playerUrl": null,
              "resultLabel": "-",
              "resultUrl": null
            },
            {
              "rank": "3.",
              "player": "-",
              "playerUrl": null,
              "resultLabel": "-",
              "resultUrl": null
            }
          ]
        },
        {
          "title": "Dirty World NMPZ",
          "mapUrl": "https://www.geoguessr.com/maps/63f3ff1e0355e40ded075e0c",
          "theme": "secondary",
          "entries": [
            {
              "rank": "1.",
              "player": "Zakerr",
              "playerUrl": "https://www.geoguessr.com/user/5ec3b73d97c8ee199c573937",
              "resultLabel": "24378",
              "resultUrl": "https://www.geoguessr.com/results/ISSDr08c5oWt2tyr"
            },
            {
              "rank": "2.",
              "player": "houmreu (Youtube)",
              "playerUrl": "https://www.geoguessr.com/user/5b571ce97135fa0e48b2d9f8",
              "resultLabel": "24348",
              "resultUrl": "https://www.geoguessr.com/results/rjDyui63NbehdCFp"
            },
            {
              "rank": "3.",
              "player": "Babrnoch",
              "playerUrl": "https://www.geoguessr.com/user/676c36f3ae31f29e4b2ef2f5",
              "resultLabel": "23629",
              "resultUrl": "https://www.geoguessr.com/game/QimolJl51EVl5dZf"
            }
          ]
        },
        {
          "title": "A Varied World 25K",
          "mapUrl": "https://www.geoguessr.com/maps/64ce812adc7614680516ff8c",
          "theme": "primary",
          "entries": [
            {
              "rank": "1.",
              "player": "Intruder",
              "playerUrl": "https://www.geoguessr.com/user/5e20d66d27ec1775f067c40c",
              "resultLabel": "00:20:21",
              "resultUrl": "https://www.geoguessr.com/game/AZoqX1VLVvIYigYA"
            },
            {
              "rank": "2.",
              "player": "-",
              "playerUrl": null,
              "resultLabel": "-",
              "resultUrl": null
            },
            {
              "rank": "3.",
              "player": "-",
              "playerUrl": null,
              "resultLabel": "-",
              "resultUrl": null
            }
          ]
        },
        {
          "title": "A Varied World NM",
          "mapUrl": "https://www.geoguessr.com/maps/64ce812adc7614680516ff8c",
          "theme": "secondary",
          "entries": [
            {
              "rank": "1.",
              "player": "Zakerr",
              "playerUrl": "https://www.geoguessr.com/user/5ec3b73d97c8ee199c573937",
              "resultLabel": "24550",
              "resultUrl": "https://www.geoguessr.com/results/26joCYzI2moHZmsc"
            },
            {
              "rank": "2.",
              "player": "Juxerr",
              "playerUrl": "https://www.geoguessr.com/user/63232556fe765bafba5ef084",
              "resultLabel": "24417",
              "resultUrl": "https://www.geoguessr.com/results/RWCDOLj7rHWNRuvn"
            },
            {
              "rank": "3.",
              "player": "houmreu (Youtube)",
              "playerUrl": "https://www.geoguessr.com/user/5b571ce97135fa0e48b2d9f8",
              "resultLabel": "24174",
              "resultUrl": "https://www.geoguessr.com/results/E83gk3Vhxr99Ppj2"
            }
          ]
        },
        {
          "title": "A Varied World NMPZ",
          "mapUrl": "https://www.geoguessr.com/maps/64ce812adc7614680516ff8c",
          "theme": "secondary",
          "entries": [
            {
              "rank": "1.",
              "player": "Zakerr",
              "playerUrl": "https://www.geoguessr.com/user/5ec3b73d97c8ee199c573937",
              "resultLabel": "24361",
              "resultUrl": "https://www.geoguessr.com/results/0UHOONRzCrPz3ekh"
            },
            {
              "rank": "2.",
              "player": "Juxerr",
              "playerUrl": "https://www.geoguessr.com/user/63232556fe765bafba5ef084",
              "resultLabel": "24018",
              "resultUrl": "https://www.geoguessr.com/results/LRWyq9GTUzT8E9Bn"
            },
            {
              "rank": "3.",
              "player": "houmreu (Youtube)",
              "playerUrl": "https://www.geoguessr.com/user/5b571ce97135fa0e48b2d9f8",
              "resultLabel": "23949",
              "resultUrl": "https://www.geoguessr.com/results/IBQK1ILjx7R9r0Re"
            }
          ]
        },
        {
          "title": "A Tweaked World 25K",
          "mapUrl": "https://www.geoguessr.com/maps/64205c50e014cf9bb1a04e01",
          "theme": "primary",
          "entries": [
            {
              "rank": "1.",
              "player": "Intruder",
              "playerUrl": "https://www.geoguessr.com/user/5e20d66d27ec1775f067c40c",
              "resultLabel": "00:05:28",
              "resultUrl": "https://www.geoguessr.com/game/QRgCI8dSiBtf7dSP"
            },
            {
              "rank": "2.",
              "player": "Fabre",
              "playerUrl": "https://www.geoguessr.com/user/5e20d66d27ec1775f067c40c",
              "resultLabel": "00:05:30",
              "resultUrl": "https://www.geoguessr.com/results/IxHipvD8Eosqw5u8"
            },
            {
              "rank": "3.",
              "player": "kaerdna",
              "playerUrl": "https://www.geoguessr.com/user/5ef9c663e454364894a3fecc",
              "resultLabel": "00:07:45",
              "resultUrl": "https://www.geoguessr.com/results/tdzZ4pClPzQd3SKr"
            }
          ]
        },
        {
          "title": "A Skewed World NMPZ",
          "mapUrl": "https://www.geoguessr.com/maps/6165f7176c26ac00016bca3d",
          "theme": "secondary",
          "entries": [
            {
              "rank": "1.",
              "player": "houmreu (Youtube)",
              "playerUrl": "https://www.geoguessr.com/user/5b571ce97135fa0e48b2d9f8",
              "resultLabel": "24052",
              "resultUrl": "https://www.geoguessr.com/results/6dAi1Ppn69NdVsrt"
            },
            {
              "rank": "2.",
              "player": "Filipes",
              "playerUrl": "https://www.geoguessr.com/user/60d61ea5548abb000175dd7c",
              "resultLabel": "23373",
              "resultUrl": "https://www.geoguessr.com/results/69tZallPnv938vMr"
            },
            {
              "rank": "3.",
              "player": "Juxerr",
              "playerUrl": "https://www.geoguessr.com/user/63232556fe765bafba5ef084",
              "resultLabel": "23319",
              "resultUrl": "https://www.geoguessr.com/results/FA02O2nHYjbMbJxC"
            }
          ]
        },
        {
          "title": "Terminus NMPZ",
          "mapUrl": "https://www.geoguessr.com/maps/64919f3c95165ff26469091a",
          "theme": "secondary",
          "entries": [
            {
              "rank": "1.",
              "player": "❤GeoPsique❤",
              "playerUrl": "https://www.geoguessr.com/user/5e6bd352b3ec1786bc33f817",
              "resultLabel": "23055",
              "resultUrl": "https://www.geoguessr.com/results/AUGgEEVOzegnfh7c"
            },
            {
              "rank": "2.",
              "player": "houmreu (Youtube)",
              "playerUrl": "https://www.geoguessr.com/user/5b571ce97135fa0e48b2d9f8",
              "resultLabel": "23027",
              "resultUrl": "https://www.geoguessr.com/results/A1MXMoWMVJIzZlyz"
            },
            {
              "rank": "3.",
              "player": "Daniel Samek",
              "playerUrl": "https://www.geoguessr.com/user/609c330b1415fe00017eb716",
              "resultLabel": "22991",
              "resultUrl": "https://www.geoguessr.com/game/FQwEnHUtsZQepjiF?shared"
            }
          ]
        }
      ]
    },
    {
      "id": "streaks",
      "header": "Streaks",
      "cards": [
        {
          "title": "Česko/Slovensko NM (Region)",
          "mapUrl": "https://www.geoguessr.com/maps/64c38117ef02543defebb815",
          "theme": "tertiary",
          "entries": [
            {
              "rank": "1.",
              "player": "-",
              "playerUrl": null,
              "resultLabel": "-",
              "resultUrl": null
            },
            {
              "rank": "2.",
              "player": "-",
              "playerUrl": null,
              "resultLabel": "-",
              "resultUrl": null
            },
            {
              "rank": "3.",
              "player": "-",
              "playerUrl": null,
              "resultLabel": "-",
              "resultUrl": null
            }
          ]
        },
        {
          "title": "Česko NM (Region)",
          "mapUrl": "https://www.geoguessr.com/maps/czech-republic",
          "theme": "tertiary",
          "entries": [
            {
              "rank": "1.",
              "player": "-",
              "playerUrl": null,
              "resultLabel": "-",
              "resultUrl": null
            },
            {
              "rank": "2.",
              "player": "-",
              "playerUrl": null,
              "resultLabel": "-",
              "resultUrl": null
            },
            {
              "rank": "3.",
              "player": "-",
              "playerUrl": null,
              "resultLabel": "-",
              "resultUrl": null
            }
          ]
        },
        {
          "title": "Slovensko NM (Region)",
          "mapUrl": "https://www.geoguessr.com/maps/slovakia",
          "theme": "tertiary",
          "entries": [
            {
              "rank": "1.",
              "player": "-",
              "playerUrl": null,
              "resultLabel": "-",
              "resultUrl": null
            },
            {
              "rank": "2.",
              "player": "-",
              "playerUrl": null,
              "resultLabel": "-",
              "resultUrl": null
            },
            {
              "rank": "3.",
              "player": "-",
              "playerUrl": null,
              "resultLabel": "-",
              "resultUrl": null
            }
          ]
        },
        {
          "title": "An Arbitrary World NM",
          "mapUrl": "https://www.geoguessr.com/maps/6089bfcff6a0770001f645dd",
          "theme": "tertiary",
          "entries": [
            {
              "rank": "1.",
              "player": "-",
              "playerUrl": null,
              "resultLabel": "-",
              "resultUrl": null
            },
            {
              "rank": "2.",
              "player": "-",
              "playerUrl": null,
              "resultLabel": "-",
              "resultUrl": null
            },
            {
              "rank": "3.",
              "player": "-",
              "playerUrl": null,
              "resultLabel": "-",
              "resultUrl": null
            }
          ]
        },
        {
          "title": "An Arbitrary World NMPZ",
          "mapUrl": "https://www.geoguessr.com/maps/6089bfcff6a0770001f645dd",
          "theme": "tertiary",
          "entries": [
            {
              "rank": "1.",
              "player": "-",
              "playerUrl": null,
              "resultLabel": "-",
              "resultUrl": null
            },
            {
              "rank": "2.",
              "player": "-",
              "playerUrl": null,
              "resultLabel": "-",
              "resultUrl": null
            },
            {
              "rank": "3.",
              "player": "-",
              "playerUrl": null,
              "resultLabel": "-",
              "resultUrl": null
            }
          ]
        },
        {
          "title": "An Arbitrary Rural World NM",
          "mapUrl": "https://www.geoguessr.com/maps/643dbc7ccc47d3a344307998",
          "theme": "tertiary",
          "entries": [
            {
              "rank": "1.",
              "player": "Filipes",
              "playerUrl": "https://www.geoguessr.com/user/60d61ea5548abb000175dd7c",
              "resultLabel": "69",
              "resultUrl": "https://www.youtube.com/watch?v=aiGwPNoAAwE"
            },
            {
              "rank": "2.",
              "player": "Zakerr",
              "playerUrl": "https://www.geoguessr.com/user/5ec3b73d97c8ee199c573937",
              "resultLabel": "35",
              "resultUrl": "https://www.youtube.com/watch?v=GjLvJ77YoWE"
            },
            {
              "rank": "3.",
              "player": "-",
              "playerUrl": null,
              "resultLabel": "-",
              "resultUrl": null
            }
          ]
        },
        {
          "title": "An Arbitrary Rural World NMPZ",
          "mapUrl": "https://www.geoguessr.com/maps/643dbc7ccc47d3a344307998",
          "theme": "tertiary",
          "entries": [
            {
              "rank": "1.",
              "player": "Zakerr",
              "playerUrl": "https://www.geoguessr.com/user/5ec3b73d97c8ee199c573937",
              "resultLabel": "63",
              "resultUrl": "https://www.youtube.com/watch?v=TkOJn1_VlOo"
            },
            {
              "rank": "2.",
              "player": "houmreu (Youtube)",
              "playerUrl": "https://www.geoguessr.com/user/5b571ce97135fa0e48b2d9f8",
              "resultLabel": "32",
              "resultUrl": "https://youtu.be/sasRh88tE3Y"
            },
            {
              "rank": "3.",
              "player": "-",
              "playerUrl": null,
              "resultLabel": "-",
              "resultUrl": null
            }
          ]
        },
        {
          "title": "An Arbitrary Europe NM",
          "mapUrl": "https://www.geoguessr.com/maps/60788ebfb15d750001929514",
          "theme": "tertiary",
          "entries": [
            {
              "rank": "1.",
              "player": "Raspberry",
              "playerUrl": "https://www.geoguessr.com/user/5e88bac13d4b6a2d8ca9f5a9",
              "resultLabel": "56",
              "resultUrl": "https://www.youtube.com/watch?v=iHdDT74PrGY"
            },
            {
              "rank": "2.",
              "player": "-",
              "playerUrl": null,
              "resultLabel": "-",
              "resultUrl": null
            },
            {
              "rank": "3.",
              "player": "-",
              "playerUrl": null,
              "resultLabel": "-",
              "resultUrl": null
            }
          ]
        },
        {
          "title": "An Arbitrary Europe NMPZ",
          "mapUrl": "https://www.geoguessr.com/maps/60788ebfb15d750001929514",
          "theme": "tertiary",
          "entries": [
            {
              "rank": "1.",
              "player": "-",
              "playerUrl": null,
              "resultLabel": "-",
              "resultUrl": null
            },
            {
              "rank": "2.",
              "player": "-",
              "playerUrl": null,
              "resultLabel": "-",
              "resultUrl": null
            },
            {
              "rank": "3.",
              "player": "-",
              "playerUrl": null,
              "resultLabel": "-",
              "resultUrl": null
            }
          ]
        },
        {
          "title": "A Skewed World NMPZ",
          "mapUrl": "https://www.geoguessr.com/maps/6165f7176c26ac00016bca3d",
          "theme": "tertiary",
          "entries": [
            {
              "rank": "1.",
              "player": "-",
              "playerUrl": null,
              "resultLabel": "-",
              "resultUrl": null
            },
            {
              "rank": "2.",
              "player": "-",
              "playerUrl": null,
              "resultLabel": "-",
              "resultUrl": null
            },
            {
              "rank": "3.",
              "player": "-",
              "playerUrl": null,
              "resultLabel": "-",
              "resultUrl": null
            }
          ]
        },
        {
          "title": "Terminus NMPZ",
          "mapUrl": "https://www.geoguessr.com/maps/64919f3c95165ff26469091a",
          "theme": "tertiary",
          "entries": [
            {
              "rank": "1.",
              "player": "-",
              "playerUrl": null,
              "resultLabel": "-",
              "resultUrl": null
            },
            {
              "rank": "2.",
              "player": "-",
              "playerUrl": null,
              "resultLabel": "-",
              "resultUrl": null
            },
            {
              "rank": "3.",
              "player": "-",
              "playerUrl": null,
              "resultLabel": "-",
              "resultUrl": null
            }
          ]
        }
      ]
    },
    {
      "id": "informace",
      "header": "Informace",
      "cards": []
    }
  ]
}